setup.py
piping/__init__.py
piping/defer.py
piping/enumerable.py
piping/processors.py
piping/stream.py
piping.egg-info/PKG-INFO
piping.egg-info/SOURCES.txt
piping.egg-info/dependency_links.txt
piping.egg-info/top_level.txt