Metadata-Version: 1.0
Name: piping
Version: 0.2.1
Summary: Python Object Pipes
Home-page: UNKNOWN
Author: Brian Lauber
Author-email: constructible.truth@gmail.com
License: UNKNOWN
Platform: UNKNOWN
